
################################################################################
<poster>Tikkes</poster>
<cache>10800</poster>
<thumbnail></thumbnail>
<fanart></fanart>
################################################################################

<item>
    <title>Talking Dead S06E01 - The Day Will Come When You Won't Be</title>
    <meta>
        <content>episode</content>
        <imdb>tt2089467</imdb>
        <tvdb>252861</tvdb>
        <tvshowtitle>Talking Dead</tvshowtitle>
        <year>2016</year>
        <title>The Day Will Come When You Won't Be</title>
        <premiered>2016-10-23</premiered>
        <season>6</season>
        <episode>1</episode>
    </meta>
    <link>
        <sublink>search</sublink>
        <sublink>searchsd</sublink>
    </link>
    <animated_thumbnail></animated_thumbnail>
    <thumbnail></thumbnail>
    <animated_fanart></animated_fanart>
    <fanart></fanart>
</item>
<item>
    <title>Talking Dead S06E02 - The Well</title>
    <meta>
        <content>episode</content>
        <imdb>tt2089467</imdb>
        <tvdb>252861</tvdb>
        <tvshowtitle>Talking Dead</tvshowtitle>
        <year>2016</year>
        <title>The Well</title>
        <premiered>2016-10-30</premiered>
        <season>6</season>
        <episode>2</episode>
    </meta>
    <link>
        <sublink>search</sublink>
        <sublink>searchsd</sublink>
    </link>
    <animated_thumbnail></animated_thumbnail>
    <thumbnail></thumbnail>
    <animated_fanart></animated_fanart>
    <fanart></fanart>
</item>
<item>
    <title>Talking Dead S06E03 - The Cell</title>
    <meta>
        <content>episode</content>
        <imdb>tt2089467</imdb>
        <tvdb>252861</tvdb>
        <tvshowtitle>Talking Dead</tvshowtitle>
        <year>2016</year>
        <title>The Cell</title>
        <premiered>2016-11-06</premiered>
        <season>6</season>
        <episode>3</episode>
    </meta>
    <link>
        <sublink>search</sublink>
        <sublink>searchsd</sublink>
    </link>
    <animated_thumbnail></animated_thumbnail>
    <thumbnail></thumbnail>
    <animated_fanart></animated_fanart>
    <fanart></fanart>
</item>
<item>
    <title>Talking Dead S06E04 - Service</title>
    <meta>
        <content>episode</content>
        <imdb>tt2089467</imdb>
        <tvdb>252861</tvdb>
        <tvshowtitle>Talking Dead</tvshowtitle>
        <year>2016</year>
        <title>Service</title>
        <premiered>2016-11-13</premiered>
        <season>6</season>
        <episode>4</episode>
    </meta>
    <link>
        <sublink>search</sublink>
        <sublink>searchsd</sublink>
    </link>
    <animated_thumbnail></animated_thumbnail>
    <thumbnail></thumbnail>
    <animated_fanart></animated_fanart>
    <fanart></fanart>
</item>
<item>
    <title>Talking Dead S06E05 - Go Getters</title>
    <meta>
        <content>episode</content>
        <imdb>tt2089467</imdb>
        <tvdb>252861</tvdb>
        <tvshowtitle>Talking Dead</tvshowtitle>
        <year>2016</year>
        <title>Go Getters</title>
        <premiered>2016-11-20</premiered>
        <season>6</season>
        <episode>5</episode>
    </meta>
    <link>
        <sublink>search</sublink>
        <sublink>searchsd</sublink>
    </link>
    <animated_thumbnail></animated_thumbnail>
    <thumbnail></thumbnail>
    <animated_fanart></animated_fanart>
    <fanart></fanart>
</item>
<item>
    <title>Talking Dead S06E06 - Swear</title>
    <meta>
        <content>episode</content>
        <imdb>tt2089467</imdb>
        <tvdb>252861</tvdb>
        <tvshowtitle>Talking Dead</tvshowtitle>
        <year>2016</year>
        <title>Swear</title>
        <premiered>2016-11-27</premiered>
        <season>6</season>
        <episode>6</episode>
    </meta>
    <link>
        <sublink>search</sublink>
        <sublink>searchsd</sublink>
    </link>
    <animated_thumbnail></animated_thumbnail>
    <thumbnail></thumbnail>
    <animated_fanart></animated_fanart>
    <fanart></fanart>
</item>
<item>
    <title>Talking Dead S06E07 - Sing Me a Song</title>
    <meta>
        <content>episode</content>
        <imdb>tt2089467</imdb>
        <tvdb>252861</tvdb>
        <tvshowtitle>Talking Dead</tvshowtitle>
        <year>2016</year>
        <title>Sing Me a Song</title>
        <premiered>2016-12-04</premiered>
        <season>6</season>
        <episode>7</episode>
    </meta>
    <link>
        <sublink>search</sublink>
        <sublink>searchsd</sublink>
    </link>
    <animated_thumbnail></animated_thumbnail>
    <thumbnail></thumbnail>
    <animated_fanart></animated_fanart>
    <fanart></fanart>
</item>
<item>
    <title>Talking Dead S06E08 - Hearts Still Beating</title>
    <meta>
        <content>episode</content>
        <imdb>tt2089467</imdb>
        <tvdb>252861</tvdb>
        <tvshowtitle>Talking Dead</tvshowtitle>
        <year>2016</year>
        <title>Hearts Still Beating</title>
        <premiered>2016-12-11</premiered>
        <season>6</season>
        <episode>8</episode>
    </meta>
    <link>
        <sublink>search</sublink>
        <sublink>searchsd</sublink>
    </link>
    <animated_thumbnail></animated_thumbnail>
    <thumbnail></thumbnail>
    <animated_fanart></animated_fanart>
    <fanart></fanart>
</item>
<item>
    <title>Talking Dead S06E09 - Rock in the Road</title>
    <meta>
        <content>episode</content>
        <imdb>tt2089467</imdb>
        <tvdb>252861</tvdb>
        <tvshowtitle>Talking Dead</tvshowtitle>
        <year>2017</year>
        <title>Rock in the Road</title>
        <premiered>2017-02-12</premiered>
        <season>6</season>
        <episode>9</episode>
    </meta>
    <link>
        <sublink>search</sublink>
        <sublink>searchsd</sublink>
    </link>
    <animated_thumbnail></animated_thumbnail>
    <thumbnail></thumbnail>
    <animated_fanart></animated_fanart>
    <fanart></fanart>
</item>
<item>
    <title>Talking Dead S06E10 - New Best Friends</title>
    <meta>
        <content>episode</content>
        <imdb>tt2089467</imdb>
        <tvdb>252861</tvdb>
        <tvshowtitle>Talking Dead</tvshowtitle>
        <year>2017</year>
        <title>New Best Friends</title>
        <premiered>2017-02-19</premiered>
        <season>6</season>
        <episode>10</episode>
    </meta>
    <link>
        <sublink>search</sublink>
        <sublink>searchsd</sublink>
    </link>
    <animated_thumbnail></animated_thumbnail>
    <thumbnail></thumbnail>
    <animated_fanart></animated_fanart>
    <fanart></fanart>
</item>
<item>
    <title>Talking Dead S06E11 - Hostiles and Calamities</title>
    <meta>
        <content>episode</content>
        <imdb>tt2089467</imdb>
        <tvdb>252861</tvdb>
        <tvshowtitle>Talking Dead</tvshowtitle>
        <year>2017</year>
        <title>Hostiles and Calamities</title>
        <premiered>2017-02-26</premiered>
        <season>6</season>
        <episode>11</episode>
    </meta>
    <link>
        <sublink>search</sublink>
        <sublink>searchsd</sublink>
    </link>
    <animated_thumbnail></animated_thumbnail>
    <thumbnail></thumbnail>
    <animated_fanart></animated_fanart>
    <fanart></fanart>
</item>
<item>
    <title>Talking Dead S06E12 - Say Yes</title>
    <meta>
        <content>episode</content>
        <imdb>tt2089467</imdb>
        <tvdb>252861</tvdb>
        <tvshowtitle>Talking Dead</tvshowtitle>
        <year>2017</year>
        <title>Say Yes</title>
        <premiered>2017-03-05</premiered>
        <season>6</season>
        <episode>12</episode>
    </meta>
    <link>
        <sublink>search</sublink>
        <sublink>searchsd</sublink>
    </link>
    <animated_thumbnail></animated_thumbnail>
    <thumbnail></thumbnail>
    <animated_fanart></animated_fanart>
    <fanart></fanart>
</item>
<item>
    <title>Talking Dead S06E13 - Bury Me Here</title>
    <meta>
        <content>episode</content>
        <imdb>tt2089467</imdb>
        <tvdb>252861</tvdb>
        <tvshowtitle>Talking Dead</tvshowtitle>
        <year>2017</year>
        <title>Bury Me Here</title>
        <premiered>2017-03-12</premiered>
        <season>6</season>
        <episode>13</episode>
    </meta>
    <link>
        <sublink>search</sublink>
        <sublink>searchsd</sublink>
    </link>
    <animated_thumbnail></animated_thumbnail>
    <thumbnail></thumbnail>
    <animated_fanart></animated_fanart>
    <fanart></fanart>
</item>
<item>
    <title>Talking Dead S06E14 - The Other Side</title>
    <meta>
        <content>episode</content>
        <imdb>tt2089467</imdb>
        <tvdb>252861</tvdb>
        <tvshowtitle>Talking Dead</tvshowtitle>
        <year>2017</year>
        <title>The Other Side</title>
        <premiered>2017-03-19</premiered>
        <season>6</season>
        <episode>14</episode>
    </meta>
    <link>
        <sublink>search</sublink>
        <sublink>searchsd</sublink>
    </link>
    <animated_thumbnail></animated_thumbnail>
    <thumbnail></thumbnail>
    <animated_fanart></animated_fanart>
    <fanart></fanart>
</item>
<item>
    <title>Talking Dead S06E15 - Something They Need</title>
    <meta>
        <content>episode</content>
        <imdb>tt2089467</imdb>
        <tvdb>252861</tvdb>
        <tvshowtitle>Talking Dead</tvshowtitle>
        <year>2017</year>
        <title>Something They Need</title>
        <premiered>2017-03-26</premiered>
        <season>6</season>
        <episode>15</episode>
    </meta>
    <link>
        <sublink>search</sublink>
        <sublink>searchsd</sublink>
    </link>
    <animated_thumbnail></animated_thumbnail>
    <thumbnail></thumbnail>
    <animated_fanart></animated_fanart>
    <fanart></fanart>
</item>
<item>
    <title>Talking Dead S06E16 - The First Day of the Rest of Your Life</title>
    <meta>
        <content>episode</content>
        <imdb>tt2089467</imdb>
        <tvdb>252861</tvdb>
        <tvshowtitle>Talking Dead</tvshowtitle>
        <year>2017</year>
        <title>The First Day of the Rest of Your Life</title>
        <premiered>2017-04-02</premiered>
        <season>6</season>
        <episode>16</episode>
    </meta>
    <link>
        <sublink>search</sublink>
        <sublink>searchsd</sublink>
    </link>
    <animated_thumbnail></animated_thumbnail>
    <thumbnail></thumbnail>
    <animated_fanart></animated_fanart>
    <fanart></fanart>
</item>
<item>
    <title>Talking Dead S06E17 - Eye of the Beholder & The New Frontier (FTWD 301/302)</title>
    <meta>
        <content>episode</content>
        <imdb>tt2089467</imdb>
        <tvdb>252861</tvdb>
        <tvshowtitle>Talking Dead</tvshowtitle>
        <year>2017</year>
        <title>Eye of the Beholder & The New Frontier (FTWD 301/302)</title>
        <premiered>2017-06-04</premiered>
        <season>6</season>
        <episode>17</episode>
    </meta>
    <link>
        <sublink>search</sublink>
        <sublink>searchsd</sublink>
    </link>
    <animated_thumbnail></animated_thumbnail>
    <thumbnail></thumbnail>
    <animated_fanart></animated_fanart>
    <fanart></fanart>
</item>
<item>
    <title>Talking Dead S06E18 - TEOTWAWKI (FTWD 303)</title>
    <meta>
        <content>episode</content>
        <imdb>tt2089467</imdb>
        <tvdb>252861</tvdb>
        <tvshowtitle>Talking Dead</tvshowtitle>
        <year>2017</year>
        <title>TEOTWAWKI (FTWD 303)</title>
        <premiered>2017-06-11</premiered>
        <season>6</season>
        <episode>18</episode>
    </meta>
    <link>
        <sublink>search</sublink>
        <sublink>searchsd</sublink>
    </link>
    <animated_thumbnail></animated_thumbnail>
    <thumbnail></thumbnail>
    <animated_fanart></animated_fanart>
    <fanart></fanart>
</item>
<item>
    <title>Talking Dead S06E19 - 100 (FTWD 304)</title>
    <meta>
        <content>episode</content>
        <imdb>tt2089467</imdb>
        <tvdb>252861</tvdb>
        <tvshowtitle>Talking Dead</tvshowtitle>
        <year>2017</year>
        <title>100 (FTWD 304)</title>
        <premiered>2017-06-18</premiered>
        <season>6</season>
        <episode>19</episode>
    </meta>
    <link>
        <sublink>search</sublink>
        <sublink>searchsd</sublink>
    </link>
    <animated_thumbnail></animated_thumbnail>
    <thumbnail></thumbnail>
    <animated_fanart></animated_fanart>
    <fanart></fanart>
</item>
<item>
    <title>Talking Dead S06E20 - Burning in Water, Drowning in Flame (FTWD 305)</title>
    <meta>
        <content>episode</content>
        <imdb>tt2089467</imdb>
        <tvdb>252861</tvdb>
        <tvshowtitle>Talking Dead</tvshowtitle>
        <year>2017</year>
        <title>Burning in Water, Drowning in Flame (FTWD 305)</title>
        <premiered>2017-06-25</premiered>
        <season>6</season>
        <episode>20</episode>
    </meta>
    <link>
        <sublink>search</sublink>
        <sublink>searchsd</sublink>
    </link>
    <animated_thumbnail></animated_thumbnail>
    <thumbnail></thumbnail>
    <animated_fanart></animated_fanart>
    <fanart></fanart>
</item>
<item>
    <title>Talking Dead S06E21 - Red Dirt (FTWD 306)</title>
    <meta>
        <content>episode</content>
        <imdb>tt2089467</imdb>
        <tvdb>252861</tvdb>
        <tvshowtitle>Talking Dead</tvshowtitle>
        <year>2017</year>
        <title>Red Dirt (FTWD 306)</title>
        <premiered>2017-07-02</premiered>
        <season>6</season>
        <episode>21</episode>
    </meta>
    <link>
        <sublink>search</sublink>
        <sublink>searchsd</sublink>
    </link>
    <animated_thumbnail></animated_thumbnail>
    <thumbnail></thumbnail>
    <animated_fanart></animated_fanart>
    <fanart></fanart>
</item>
<item>
    <title>Talking Dead S06E22 - The Unveiling; Children of Wrath (FTWD 307/308)</title>
    <meta>
        <content>episode</content>
        <imdb>tt2089467</imdb>
        <tvdb>252861</tvdb>
        <tvshowtitle>Talking Dead</tvshowtitle>
        <year>2017</year>
        <title>The Unveiling; Children of Wrath (FTWD 307/308)</title>
        <premiered>2017-07-09</premiered>
        <season>6</season>
        <episode>22</episode>
    </meta>
    <link>
        <sublink>search</sublink>
        <sublink>searchsd</sublink>
    </link>
    <animated_thumbnail></animated_thumbnail>
    <thumbnail></thumbnail>
    <animated_fanart></animated_fanart>
    <fanart></fanart>
</item>
<item>
    <title>Talking Dead S06E23 - Minotaur; The Diviner (FTWD 309/310)</title>
    <meta>
        <content>episode</content>
        <imdb>tt2089467</imdb>
        <tvdb>252861</tvdb>
        <tvshowtitle>Talking Dead</tvshowtitle>
        <year>2017</year>
        <title>Minotaur; The Diviner (FTWD 309/310)</title>
        <premiered>2017-09-10</premiered>
        <season>6</season>
        <episode>23</episode>
    </meta>
    <link>
        <sublink>search</sublink>
        <sublink>searchsd</sublink>
    </link>
    <animated_thumbnail></animated_thumbnail>
    <thumbnail></thumbnail>
    <animated_fanart></animated_fanart>
    <fanart></fanart>
</item>
<item>
    <title>Talking Dead S06E24 - La Serpiente (FTWD 311)</title>
    <meta>
        <content>episode</content>
        <imdb>tt2089467</imdb>
        <tvdb>252861</tvdb>
        <tvshowtitle>Talking Dead</tvshowtitle>
        <year>2017</year>
        <title>La Serpiente (FTWD 311)</title>
        <premiered>2017-09-17</premiered>
        <season>6</season>
        <episode>24</episode>
    </meta>
    <link>
        <sublink>search</sublink>
        <sublink>searchsd</sublink>
    </link>
    <animated_thumbnail></animated_thumbnail>
    <thumbnail></thumbnail>
    <animated_fanart></animated_fanart>
    <fanart></fanart>
</item>
<item>
    <title>Talking Dead S06E25 - Brother's Keeper (FTWD 312)</title>
    <meta>
        <content>episode</content>
        <imdb>tt2089467</imdb>
        <tvdb>252861</tvdb>
        <tvshowtitle>Talking Dead</tvshowtitle>
        <year>2017</year>
        <title>Brother's Keeper (FTWD 312)</title>
        <premiered>2017-09-24</premiered>
        <season>6</season>
        <episode>25</episode>
    </meta>
    <link>
        <sublink>search</sublink>
        <sublink>searchsd</sublink>
    </link>
    <animated_thumbnail></animated_thumbnail>
    <thumbnail></thumbnail>
    <animated_fanart></animated_fanart>
    <fanart></fanart>
</item>
<item>
    <title>Talking Dead S06E26 - This Land Is Your Land (FTWD 313)</title>
    <meta>
        <content>episode</content>
        <imdb>tt2089467</imdb>
        <tvdb>252861</tvdb>
        <tvshowtitle>Talking Dead</tvshowtitle>
        <year>2017</year>
        <title>This Land Is Your Land (FTWD 313)</title>
        <premiered>2017-10-01</premiered>
        <season>6</season>
        <episode>26</episode>
    </meta>
    <link>
        <sublink>search</sublink>
        <sublink>searchsd</sublink>
    </link>
    <animated_thumbnail></animated_thumbnail>
    <thumbnail></thumbnail>
    <animated_fanart></animated_fanart>
    <fanart></fanart>
</item>
<item>
    <title>Talking Dead S06E27 - El Matadero (FTWD 314)</title>
    <meta>
        <content>episode</content>
        <imdb>tt2089467</imdb>
        <tvdb>252861</tvdb>
        <tvshowtitle>Talking Dead</tvshowtitle>
        <year>2017</year>
        <title>El Matadero (FTWD 314)</title>
        <premiered>2017-10-08</premiered>
        <season>6</season>
        <episode>27</episode>
    </meta>
    <link>
        <sublink>search</sublink>
        <sublink>searchsd</sublink>
    </link>
    <animated_thumbnail></animated_thumbnail>
    <thumbnail></thumbnail>
    <animated_fanart></animated_fanart>
    <fanart></fanart>
</item>
<item>
    <title>Talking Dead S06E28 - Things Bad Begun; Sleigh Ride (FTWD 315/316)</title>
    <meta>
        <content>episode</content>
        <imdb>tt2089467</imdb>
        <tvdb>252861</tvdb>
        <tvshowtitle>Talking Dead</tvshowtitle>
        <year>2017</year>
        <title>Things Bad Begun; Sleigh Ride (FTWD 315/316)</title>
        <premiered>2017-10-15</premiered>
        <season>6</season>
        <episode>28</episode>
    </meta>
    <link>
        <sublink>search</sublink>
        <sublink>searchsd</sublink>
    </link>
    <animated_thumbnail></animated_thumbnail>
    <thumbnail></thumbnail>
    <animated_fanart></animated_fanart>
    <fanart></fanart>
</item>