
################################################################################
<poster>Tikkes</poster>
<cache>10800</poster>
<thumbnail></thumbnail>
<fanart></fanart>
################################################################################

<item>
    <title>Star Trek: Voyager S01E01 - Caretaker (1)</title>
    <meta>
        <content>episode</content>
        <imdb>tt0112178</imdb>
        <tvdb>74550</tvdb>
        <tvshowtitle>Star Trek: Voyager</tvshowtitle>
        <year>1995</year>
        <title>Caretaker (1)</title>
        <premiered>1995-01-16</premiered>
        <season>1</season>
        <episode>1</episode>
    </meta>
    <link>
        <sublink>search</sublink>
        <sublink>searchsd</sublink>
    </link>
    <animated_thumbnail></animated_thumbnail>
    <thumbnail></thumbnail>
    <animated_fanart></animated_fanart>
    <fanart></fanart>
</item>
<item>
    <title>Star Trek: Voyager S01E02 - Caretaker (2)</title>
    <meta>
        <content>episode</content>
        <imdb>tt0112178</imdb>
        <tvdb>74550</tvdb>
        <tvshowtitle>Star Trek: Voyager</tvshowtitle>
        <year>1995</year>
        <title>Caretaker (2)</title>
        <premiered>1995-01-16</premiered>
        <season>1</season>
        <episode>2</episode>
    </meta>
    <link>
        <sublink>search</sublink>
        <sublink>searchsd</sublink>
    </link>
    <animated_thumbnail></animated_thumbnail>
    <thumbnail></thumbnail>
    <animated_fanart></animated_fanart>
    <fanart></fanart>
</item>
<item>
    <title>Star Trek: Voyager S01E03 - Parallax</title>
    <meta>
        <content>episode</content>
        <imdb>tt0112178</imdb>
        <tvdb>74550</tvdb>
        <tvshowtitle>Star Trek: Voyager</tvshowtitle>
        <year>1995</year>
        <title>Parallax</title>
        <premiered>1995-01-23</premiered>
        <season>1</season>
        <episode>3</episode>
    </meta>
    <link>
        <sublink>search</sublink>
        <sublink>searchsd</sublink>
    </link>
    <animated_thumbnail></animated_thumbnail>
    <thumbnail></thumbnail>
    <animated_fanart></animated_fanart>
    <fanart></fanart>
</item>
<item>
    <title>Star Trek: Voyager S01E04 - Time and Again</title>
    <meta>
        <content>episode</content>
        <imdb>tt0112178</imdb>
        <tvdb>74550</tvdb>
        <tvshowtitle>Star Trek: Voyager</tvshowtitle>
        <year>1995</year>
        <title>Time and Again</title>
        <premiered>1995-01-30</premiered>
        <season>1</season>
        <episode>4</episode>
    </meta>
    <link>
        <sublink>search</sublink>
        <sublink>searchsd</sublink>
    </link>
    <animated_thumbnail></animated_thumbnail>
    <thumbnail></thumbnail>
    <animated_fanart></animated_fanart>
    <fanart></fanart>
</item>
<item>
    <title>Star Trek: Voyager S01E05 - Phage</title>
    <meta>
        <content>episode</content>
        <imdb>tt0112178</imdb>
        <tvdb>74550</tvdb>
        <tvshowtitle>Star Trek: Voyager</tvshowtitle>
        <year>1995</year>
        <title>Phage</title>
        <premiered>1995-02-06</premiered>
        <season>1</season>
        <episode>5</episode>
    </meta>
    <link>
        <sublink>search</sublink>
        <sublink>searchsd</sublink>
    </link>
    <animated_thumbnail></animated_thumbnail>
    <thumbnail></thumbnail>
    <animated_fanart></animated_fanart>
    <fanart></fanart>
</item>
<item>
    <title>Star Trek: Voyager S01E06 - The Cloud</title>
    <meta>
        <content>episode</content>
        <imdb>tt0112178</imdb>
        <tvdb>74550</tvdb>
        <tvshowtitle>Star Trek: Voyager</tvshowtitle>
        <year>1995</year>
        <title>The Cloud</title>
        <premiered>1995-02-13</premiered>
        <season>1</season>
        <episode>6</episode>
    </meta>
    <link>
        <sublink>search</sublink>
        <sublink>searchsd</sublink>
    </link>
    <animated_thumbnail></animated_thumbnail>
    <thumbnail></thumbnail>
    <animated_fanart></animated_fanart>
    <fanart></fanart>
</item>
<item>
    <title>Star Trek: Voyager S01E07 - Eye of the Needle</title>
    <meta>
        <content>episode</content>
        <imdb>tt0112178</imdb>
        <tvdb>74550</tvdb>
        <tvshowtitle>Star Trek: Voyager</tvshowtitle>
        <year>1995</year>
        <title>Eye of the Needle</title>
        <premiered>1995-02-20</premiered>
        <season>1</season>
        <episode>7</episode>
    </meta>
    <link>
        <sublink>search</sublink>
        <sublink>searchsd</sublink>
    </link>
    <animated_thumbnail></animated_thumbnail>
    <thumbnail></thumbnail>
    <animated_fanart></animated_fanart>
    <fanart></fanart>
</item>
<item>
    <title>Star Trek: Voyager S01E08 - Ex Post Facto</title>
    <meta>
        <content>episode</content>
        <imdb>tt0112178</imdb>
        <tvdb>74550</tvdb>
        <tvshowtitle>Star Trek: Voyager</tvshowtitle>
        <year>1995</year>
        <title>Ex Post Facto</title>
        <premiered>1995-02-27</premiered>
        <season>1</season>
        <episode>8</episode>
    </meta>
    <link>
        <sublink>search</sublink>
        <sublink>searchsd</sublink>
    </link>
    <animated_thumbnail></animated_thumbnail>
    <thumbnail></thumbnail>
    <animated_fanart></animated_fanart>
    <fanart></fanart>
</item>
<item>
    <title>Star Trek: Voyager S01E09 - Emanations</title>
    <meta>
        <content>episode</content>
        <imdb>tt0112178</imdb>
        <tvdb>74550</tvdb>
        <tvshowtitle>Star Trek: Voyager</tvshowtitle>
        <year>1995</year>
        <title>Emanations</title>
        <premiered>1995-03-13</premiered>
        <season>1</season>
        <episode>9</episode>
    </meta>
    <link>
        <sublink>search</sublink>
        <sublink>searchsd</sublink>
    </link>
    <animated_thumbnail></animated_thumbnail>
    <thumbnail></thumbnail>
    <animated_fanart></animated_fanart>
    <fanart></fanart>
</item>
<item>
    <title>Star Trek: Voyager S01E10 - Prime Factors</title>
    <meta>
        <content>episode</content>
        <imdb>tt0112178</imdb>
        <tvdb>74550</tvdb>
        <tvshowtitle>Star Trek: Voyager</tvshowtitle>
        <year>1995</year>
        <title>Prime Factors</title>
        <premiered>1995-03-20</premiered>
        <season>1</season>
        <episode>10</episode>
    </meta>
    <link>
        <sublink>search</sublink>
        <sublink>searchsd</sublink>
    </link>
    <animated_thumbnail></animated_thumbnail>
    <thumbnail></thumbnail>
    <animated_fanart></animated_fanart>
    <fanart></fanart>
</item>
<item>
    <title>Star Trek: Voyager S01E11 - State of Flux</title>
    <meta>
        <content>episode</content>
        <imdb>tt0112178</imdb>
        <tvdb>74550</tvdb>
        <tvshowtitle>Star Trek: Voyager</tvshowtitle>
        <year>1995</year>
        <title>State of Flux</title>
        <premiered>1995-04-10</premiered>
        <season>1</season>
        <episode>11</episode>
    </meta>
    <link>
        <sublink>search</sublink>
        <sublink>searchsd</sublink>
    </link>
    <animated_thumbnail></animated_thumbnail>
    <thumbnail></thumbnail>
    <animated_fanart></animated_fanart>
    <fanart></fanart>
</item>
<item>
    <title>Star Trek: Voyager S01E12 - Heroes and Demons</title>
    <meta>
        <content>episode</content>
        <imdb>tt0112178</imdb>
        <tvdb>74550</tvdb>
        <tvshowtitle>Star Trek: Voyager</tvshowtitle>
        <year>1995</year>
        <title>Heroes and Demons</title>
        <premiered>1995-04-24</premiered>
        <season>1</season>
        <episode>12</episode>
    </meta>
    <link>
        <sublink>search</sublink>
        <sublink>searchsd</sublink>
    </link>
    <animated_thumbnail></animated_thumbnail>
    <thumbnail></thumbnail>
    <animated_fanart></animated_fanart>
    <fanart></fanart>
</item>
<item>
    <title>Star Trek: Voyager S01E13 - Cathexis</title>
    <meta>
        <content>episode</content>
        <imdb>tt0112178</imdb>
        <tvdb>74550</tvdb>
        <tvshowtitle>Star Trek: Voyager</tvshowtitle>
        <year>1995</year>
        <title>Cathexis</title>
        <premiered>1995-05-01</premiered>
        <season>1</season>
        <episode>13</episode>
    </meta>
    <link>
        <sublink>search</sublink>
        <sublink>searchsd</sublink>
    </link>
    <animated_thumbnail></animated_thumbnail>
    <thumbnail></thumbnail>
    <animated_fanart></animated_fanart>
    <fanart></fanart>
</item>
<item>
    <title>Star Trek: Voyager S01E14 - Faces</title>
    <meta>
        <content>episode</content>
        <imdb>tt0112178</imdb>
        <tvdb>74550</tvdb>
        <tvshowtitle>Star Trek: Voyager</tvshowtitle>
        <year>1995</year>
        <title>Faces</title>
        <premiered>1995-05-08</premiered>
        <season>1</season>
        <episode>14</episode>
    </meta>
    <link>
        <sublink>search</sublink>
        <sublink>searchsd</sublink>
    </link>
    <animated_thumbnail></animated_thumbnail>
    <thumbnail></thumbnail>
    <animated_fanart></animated_fanart>
    <fanart></fanart>
</item>
<item>
    <title>Star Trek: Voyager S01E15 - Jetrel</title>
    <meta>
        <content>episode</content>
        <imdb>tt0112178</imdb>
        <tvdb>74550</tvdb>
        <tvshowtitle>Star Trek: Voyager</tvshowtitle>
        <year>1995</year>
        <title>Jetrel</title>
        <premiered>1995-05-15</premiered>
        <season>1</season>
        <episode>15</episode>
    </meta>
    <link>
        <sublink>search</sublink>
        <sublink>searchsd</sublink>
    </link>
    <animated_thumbnail></animated_thumbnail>
    <thumbnail></thumbnail>
    <animated_fanart></animated_fanart>
    <fanart></fanart>
</item>
<item>
    <title>Star Trek: Voyager S01E16 - Learning Curve</title>
    <meta>
        <content>episode</content>
        <imdb>tt0112178</imdb>
        <tvdb>74550</tvdb>
        <tvshowtitle>Star Trek: Voyager</tvshowtitle>
        <year>1995</year>
        <title>Learning Curve</title>
        <premiered>1995-05-22</premiered>
        <season>1</season>
        <episode>16</episode>
    </meta>
    <link>
        <sublink>search</sublink>
        <sublink>searchsd</sublink>
    </link>
    <animated_thumbnail></animated_thumbnail>
    <thumbnail></thumbnail>
    <animated_fanart></animated_fanart>
    <fanart></fanart>
</item>