
################################################################################################################################
<poster>Tikkes</poster>
<cache>10800</poster>
<thumbnail></thumbnail>
<fanart></fanart>
################################################################################################################################

<item>
    <title>Grey's Anatomy S11E01 - I Must Have Lost It on the Wind</title>
    <meta>
        <content>episode</content>
        <imdb>tt0413573</imdb>
        <tvdb>73762</tvdb>
        <tvshowtitle>Grey's Anatomy</tvshowtitle>
        <year>2014</year>
        <title>I Must Have Lost It on the Wind</title>
        <premiered>2014-09-25</premiered>
        <season>11</season>
        <episode>1</episode>
    </meta>
    <link>
        <sublink>search</sublink>
        <sublink>searchsd</sublink>
    </link>
    <animated_thumbnail></animated_thumbnail>
    <thumbnail></thumbnail>
    <animated_fanart></animated_fanart>
    <fanart></fanart>
</item>
<item>
    <title>Grey's Anatomy S11E02 - Puzzle With a Piece Missing</title>
    <meta>
        <content>episode</content>
        <imdb>tt0413573</imdb>
        <tvdb>73762</tvdb>
        <tvshowtitle>Grey's Anatomy</tvshowtitle>
        <year>2014</year>
        <title>Puzzle With a Piece Missing</title>
        <premiered>2014-10-02</premiered>
        <season>11</season>
        <episode>2</episode>
    </meta>
    <link>
        <sublink>search</sublink>
        <sublink>searchsd</sublink>
    </link>
    <animated_thumbnail></animated_thumbnail>
    <thumbnail></thumbnail>
    <animated_fanart></animated_fanart>
    <fanart></fanart>
</item>
<item>
    <title>Grey's Anatomy S11E03 - Got to Be Real</title>
    <meta>
        <content>episode</content>
        <imdb>tt0413573</imdb>
        <tvdb>73762</tvdb>
        <tvshowtitle>Grey's Anatomy</tvshowtitle>
        <year>2014</year>
        <title>Got to Be Real</title>
        <premiered>2014-10-09</premiered>
        <season>11</season>
        <episode>3</episode>
    </meta>
    <link>
        <sublink>search</sublink>
        <sublink>searchsd</sublink>
    </link>
    <animated_thumbnail></animated_thumbnail>
    <thumbnail></thumbnail>
    <animated_fanart></animated_fanart>
    <fanart></fanart>
</item>
<item>
    <title>Grey's Anatomy S11E04 - Only Mama Knows</title>
    <meta>
        <content>episode</content>
        <imdb>tt0413573</imdb>
        <tvdb>73762</tvdb>
        <tvshowtitle>Grey's Anatomy</tvshowtitle>
        <year>2014</year>
        <title>Only Mama Knows</title>
        <premiered>2014-10-16</premiered>
        <season>11</season>
        <episode>4</episode>
    </meta>
    <link>
        <sublink>search</sublink>
        <sublink>searchsd</sublink>
    </link>
    <animated_thumbnail></animated_thumbnail>
    <thumbnail></thumbnail>
    <animated_fanart></animated_fanart>
    <fanart></fanart>
</item>
<item>
    <title>Grey's Anatomy S11E05 - Bend and Break</title>
    <meta>
        <content>episode</content>
        <imdb>tt0413573</imdb>
        <tvdb>73762</tvdb>
        <tvshowtitle>Grey's Anatomy</tvshowtitle>
        <year>2014</year>
        <title>Bend and Break</title>
        <premiered>2014-10-23</premiered>
        <season>11</season>
        <episode>5</episode>
    </meta>
    <link>
        <sublink>search</sublink>
        <sublink>searchsd</sublink>
    </link>
    <animated_thumbnail></animated_thumbnail>
    <thumbnail></thumbnail>
    <animated_fanart></animated_fanart>
    <fanart></fanart>
</item>
<item>
    <title>Grey's Anatomy S11E06 - Don't Let's Start</title>
    <meta>
        <content>episode</content>
        <imdb>tt0413573</imdb>
        <tvdb>73762</tvdb>
        <tvshowtitle>Grey's Anatomy</tvshowtitle>
        <year>2014</year>
        <title>Don't Let's Start</title>
        <premiered>2014-11-06</premiered>
        <season>11</season>
        <episode>6</episode>
    </meta>
    <link>
        <sublink>search</sublink>
        <sublink>searchsd</sublink>
    </link>
    <animated_thumbnail></animated_thumbnail>
    <thumbnail></thumbnail>
    <animated_fanart></animated_fanart>
    <fanart></fanart>
</item>
<item>
    <title>Grey's Anatomy S11E07 - Could We Start Again, Please?</title>
    <meta>
        <content>episode</content>
        <imdb>tt0413573</imdb>
        <tvdb>73762</tvdb>
        <tvshowtitle>Grey's Anatomy</tvshowtitle>
        <year>2014</year>
        <title>Could We Start Again, Please?</title>
        <premiered>2014-11-13</premiered>
        <season>11</season>
        <episode>7</episode>
    </meta>
    <link>
        <sublink>search</sublink>
        <sublink>searchsd</sublink>
    </link>
    <animated_thumbnail></animated_thumbnail>
    <thumbnail></thumbnail>
    <animated_fanart></animated_fanart>
    <fanart></fanart>
</item>
<item>
    <title>Grey's Anatomy S11E08 - Risk</title>
    <meta>
        <content>episode</content>
        <imdb>tt0413573</imdb>
        <tvdb>73762</tvdb>
        <tvshowtitle>Grey's Anatomy</tvshowtitle>
        <year>2014</year>
        <title>Risk</title>
        <premiered>2014-11-20</premiered>
        <season>11</season>
        <episode>8</episode>
    </meta>
    <link>
        <sublink>search</sublink>
        <sublink>searchsd</sublink>
    </link>
    <animated_thumbnail></animated_thumbnail>
    <thumbnail></thumbnail>
    <animated_fanart></animated_fanart>
    <fanart></fanart>
</item>
<item>
    <title>Grey's Anatomy S11E09 - Where Do We Go From Here?</title>
    <meta>
        <content>episode</content>
        <imdb>tt0413573</imdb>
        <tvdb>73762</tvdb>
        <tvshowtitle>Grey's Anatomy</tvshowtitle>
        <year>2015</year>
        <title>Where Do We Go From Here?</title>
        <premiered>2015-01-29</premiered>
        <season>11</season>
        <episode>9</episode>
    </meta>
    <link>
        <sublink>search</sublink>
        <sublink>searchsd</sublink>
    </link>
    <animated_thumbnail></animated_thumbnail>
    <thumbnail></thumbnail>
    <animated_fanart></animated_fanart>
    <fanart></fanart>
</item>
<item>
    <title>Grey's Anatomy S11E10 - The Bed's Too Big Without You</title>
    <meta>
        <content>episode</content>
        <imdb>tt0413573</imdb>
        <tvdb>73762</tvdb>
        <tvshowtitle>Grey's Anatomy</tvshowtitle>
        <year>2015</year>
        <title>The Bed's Too Big Without You</title>
        <premiered>2015-02-05</premiered>
        <season>11</season>
        <episode>10</episode>
    </meta>
    <link>
        <sublink>search</sublink>
        <sublink>searchsd</sublink>
    </link>
    <animated_thumbnail></animated_thumbnail>
    <thumbnail></thumbnail>
    <animated_fanart></animated_fanart>
    <fanart></fanart>
</item>
<item>
    <title>Grey's Anatomy S11E11 - All I Could Do Was Cry</title>
    <meta>
        <content>episode</content>
        <imdb>tt0413573</imdb>
        <tvdb>73762</tvdb>
        <tvshowtitle>Grey's Anatomy</tvshowtitle>
        <year>2015</year>
        <title>All I Could Do Was Cry</title>
        <premiered>2015-02-12</premiered>
        <season>11</season>
        <episode>11</episode>
    </meta>
    <link>
        <sublink>search</sublink>
        <sublink>searchsd</sublink>
    </link>
    <animated_thumbnail></animated_thumbnail>
    <thumbnail></thumbnail>
    <animated_fanart></animated_fanart>
    <fanart></fanart>
</item>
<item>
    <title>Grey's Anatomy S11E12 - The Great Pretender</title>
    <meta>
        <content>episode</content>
        <imdb>tt0413573</imdb>
        <tvdb>73762</tvdb>
        <tvshowtitle>Grey's Anatomy</tvshowtitle>
        <year>2015</year>
        <title>The Great Pretender</title>
        <premiered>2015-02-19</premiered>
        <season>11</season>
        <episode>12</episode>
    </meta>
    <link>
        <sublink>search</sublink>
        <sublink>searchsd</sublink>
    </link>
    <animated_thumbnail></animated_thumbnail>
    <thumbnail></thumbnail>
    <animated_fanart></animated_fanart>
    <fanart></fanart>
</item>
<item>
    <title>Grey's Anatomy S11E13 - Staring at the End</title>
    <meta>
        <content>episode</content>
        <imdb>tt0413573</imdb>
        <tvdb>73762</tvdb>
        <tvshowtitle>Grey's Anatomy</tvshowtitle>
        <year>2015</year>
        <title>Staring at the End</title>
        <premiered>2015-02-26</premiered>
        <season>11</season>
        <episode>13</episode>
    </meta>
    <link>
        <sublink>search</sublink>
        <sublink>searchsd</sublink>
    </link>
    <animated_thumbnail></animated_thumbnail>
    <thumbnail></thumbnail>
    <animated_fanart></animated_fanart>
    <fanart></fanart>
</item>
<item>
    <title>Grey's Anatomy S11E14 - The Distance</title>
    <meta>
        <content>episode</content>
        <imdb>tt0413573</imdb>
        <tvdb>73762</tvdb>
        <tvshowtitle>Grey's Anatomy</tvshowtitle>
        <year>2015</year>
        <title>The Distance</title>
        <premiered>2015-03-05</premiered>
        <season>11</season>
        <episode>14</episode>
    </meta>
    <link>
        <sublink>search</sublink>
        <sublink>searchsd</sublink>
    </link>
    <animated_thumbnail></animated_thumbnail>
    <thumbnail></thumbnail>
    <animated_fanart></animated_fanart>
    <fanart></fanart>
</item>
<item>
    <title>Grey's Anatomy S11E15 - I Feel the Earth Move</title>
    <meta>
        <content>episode</content>
        <imdb>tt0413573</imdb>
        <tvdb>73762</tvdb>
        <tvshowtitle>Grey's Anatomy</tvshowtitle>
        <year>2015</year>
        <title>I Feel the Earth Move</title>
        <premiered>2015-03-12</premiered>
        <season>11</season>
        <episode>15</episode>
    </meta>
    <link>
        <sublink>search</sublink>
        <sublink>searchsd</sublink>
    </link>
    <animated_thumbnail></animated_thumbnail>
    <thumbnail></thumbnail>
    <animated_fanart></animated_fanart>
    <fanart></fanart>
</item>
<item>
    <title>Grey's Anatomy S11E16 - Don't Dream It's Over</title>
    <meta>
        <content>episode</content>
        <imdb>tt0413573</imdb>
        <tvdb>73762</tvdb>
        <tvshowtitle>Grey's Anatomy</tvshowtitle>
        <year>2015</year>
        <title>Don't Dream It's Over</title>
        <premiered>2015-03-19</premiered>
        <season>11</season>
        <episode>16</episode>
    </meta>
    <link>
        <sublink>search</sublink>
        <sublink>searchsd</sublink>
    </link>
    <animated_thumbnail></animated_thumbnail>
    <thumbnail></thumbnail>
    <animated_fanart></animated_fanart>
    <fanart></fanart>
</item>
<item>
    <title>Grey's Anatomy S11E17 - With or Without You</title>
    <meta>
        <content>episode</content>
        <imdb>tt0413573</imdb>
        <tvdb>73762</tvdb>
        <tvshowtitle>Grey's Anatomy</tvshowtitle>
        <year>2015</year>
        <title>With or Without You</title>
        <premiered>2015-03-26</premiered>
        <season>11</season>
        <episode>17</episode>
    </meta>
    <link>
        <sublink>search</sublink>
        <sublink>searchsd</sublink>
    </link>
    <animated_thumbnail></animated_thumbnail>
    <thumbnail></thumbnail>
    <animated_fanart></animated_fanart>
    <fanart></fanart>
</item>
<item>
    <title>Grey's Anatomy S11E18 - When I Grow Up</title>
    <meta>
        <content>episode</content>
        <imdb>tt0413573</imdb>
        <tvdb>73762</tvdb>
        <tvshowtitle>Grey's Anatomy</tvshowtitle>
        <year>2015</year>
        <title>When I Grow Up</title>
        <premiered>2015-04-02</premiered>
        <season>11</season>
        <episode>18</episode>
    </meta>
    <link>
        <sublink>search</sublink>
        <sublink>searchsd</sublink>
    </link>
    <animated_thumbnail></animated_thumbnail>
    <thumbnail></thumbnail>
    <animated_fanart></animated_fanart>
    <fanart></fanart>
</item>
<item>
    <title>Grey's Anatomy S11E19 - Crazy Love</title>
    <meta>
        <content>episode</content>
        <imdb>tt0413573</imdb>
        <tvdb>73762</tvdb>
        <tvshowtitle>Grey's Anatomy</tvshowtitle>
        <year>2015</year>
        <title>Crazy Love</title>
        <premiered>2015-04-09</premiered>
        <season>11</season>
        <episode>19</episode>
    </meta>
    <link>
        <sublink>search</sublink>
        <sublink>searchsd</sublink>
    </link>
    <animated_thumbnail></animated_thumbnail>
    <thumbnail></thumbnail>
    <animated_fanart></animated_fanart>
    <fanart></fanart>
</item>
<item>
    <title>Grey's Anatomy S11E20 - One Flight Down</title>
    <meta>
        <content>episode</content>
        <imdb>tt0413573</imdb>
        <tvdb>73762</tvdb>
        <tvshowtitle>Grey's Anatomy</tvshowtitle>
        <year>2015</year>
        <title>One Flight Down</title>
        <premiered>2015-04-16</premiered>
        <season>11</season>
        <episode>20</episode>
    </meta>
    <link>
        <sublink>search</sublink>
        <sublink>searchsd</sublink>
    </link>
    <animated_thumbnail></animated_thumbnail>
    <thumbnail></thumbnail>
    <animated_fanart></animated_fanart>
    <fanart></fanart>
</item>
<item>
    <title>Grey's Anatomy S11E21 - How to Save a Life</title>
    <meta>
        <content>episode</content>
        <imdb>tt0413573</imdb>
        <tvdb>73762</tvdb>
        <tvshowtitle>Grey's Anatomy</tvshowtitle>
        <year>2015</year>
        <title>How to Save a Life</title>
        <premiered>2015-04-23</premiered>
        <season>11</season>
        <episode>21</episode>
    </meta>
    <link>
        <sublink>search</sublink>
        <sublink>searchsd</sublink>
    </link>
    <animated_thumbnail></animated_thumbnail>
    <thumbnail></thumbnail>
    <animated_fanart></animated_fanart>
    <fanart></fanart>
</item>
<item>
    <title>Grey's Anatomy S11E22 - She's Leaving Home</title>
    <meta>
        <content>episode</content>
        <imdb>tt0413573</imdb>
        <tvdb>73762</tvdb>
        <tvshowtitle>Grey's Anatomy</tvshowtitle>
        <year>2015</year>
        <title>She's Leaving Home</title>
        <premiered>2015-04-30</premiered>
        <season>11</season>
        <episode>22</episode>
    </meta>
    <link>
        <sublink>search</sublink>
        <sublink>searchsd</sublink>
    </link>
    <animated_thumbnail></animated_thumbnail>
    <thumbnail></thumbnail>
    <animated_fanart></animated_fanart>
    <fanart></fanart>
</item>
<item>
    <title>Grey's Anatomy S11E23 - Time Stops</title>
    <meta>
        <content>episode</content>
        <imdb>tt0413573</imdb>
        <tvdb>73762</tvdb>
        <tvshowtitle>Grey's Anatomy</tvshowtitle>
        <year>2015</year>
        <title>Time Stops</title>
        <premiered>2015-05-07</premiered>
        <season>11</season>
        <episode>23</episode>
    </meta>
    <link>
        <sublink>search</sublink>
        <sublink>searchsd</sublink>
    </link>
    <animated_thumbnail></animated_thumbnail>
    <thumbnail></thumbnail>
    <animated_fanart></animated_fanart>
    <fanart></fanart>
</item>
<item>
    <title>Grey's Anatomy S11E24 - You're My Home</title>
    <meta>
        <content>episode</content>
        <imdb>tt0413573</imdb>
        <tvdb>73762</tvdb>
        <tvshowtitle>Grey's Anatomy</tvshowtitle>
        <year>2015</year>
        <title>You're My Home</title>
        <premiered>2015-05-14</premiered>
        <season>11</season>
        <episode>24</episode>
    </meta>
    <link>
        <sublink>search</sublink>
        <sublink>searchsd</sublink>
    </link>
    <animated_thumbnail></animated_thumbnail>
    <thumbnail></thumbnail>
    <animated_fanart></animated_fanart>
    <fanart></fanart>
</item>