#####################################################################################################################################
<poster>LaffinAtcha</poster)
<thumbnail></thumbnail>
<fanart></fanart>
#####################################################################################################################################


<item>
        <title>Mother! (2017)</title>
        <meta>
                <content>movie</content>
                <imdb>tt5109784</imdb>
                <title>Mother!</title>
                <year>2017</year>
        </meta>
        <link>
                <sublink>search</sublink>
                <sublink>searchsd</sublink>
        </link>
        <animated_thumbnail></animated_thumbnail>
        <thumbnail>https://image.tmdb.org/t/p/original/m2Tc48MkhPWYaz0f0IMuIMJlGND.jpg</thumbnail>
        <animated_fanart></animated_fanart>
        <fanart>https://image.tmdb.org/t/p/original/zIECvIGqXuDZbA8OV3hSgdETdvv.jpg</fanart>
</item>
<item>
        <title>Dunkirk (2017)</title>
        <meta>
                <content>movie</content>
                <imdb>tt5013056</imdb>
                <title>Dunkirk</title>
                <year>2017</year>
        </meta>
        <link>
                <sublink>search</sublink>
                <sublink>searchsd</sublink>
        </link>
        <animated_thumbnail></animated_thumbnail>
        <thumbnail>https://image.tmdb.org/t/p/original/bOXBV303Fgkzn2K4FeKDc0O31q4.jpg</thumbnail>
        <animated_fanart></animated_fanart>
        <fanart>https://image.tmdb.org/t/p/original/4yjJNAgXBmzxpS6sogj4ftwd270.jpg</fanart>
</item>
<item>
        <title>Kingsman: The Golden Circle 2017</title>
        <meta>
                <content>movie</content>
                <imdb>tt4649466</imdb>
                <title>Kingsman: The Golden Circle</title>
                <year>2017</year>
        </meta>
        <link>
                <sublink>search</sublink>
                <sublink>searchsd</sublink>
        </link>
        <animated_thumbnail></animated_thumbnail>
        <thumbnail>https://image.tmdb.org/t/p/original/34xBL6BXNYFqtHO9zhcgoakS4aP.jpg</thumbnail>
        <animated_fanart></animated_fanart>
        <fanart>https://image.tmdb.org/t/p/original/vLsw44dKHp1LhGCmcv3Pv6LXgEH.jpg</fanart>
</item>

<item>
        <title>American Made (2017)</title>
        <meta>
                <content>movie</content>
                <imdb>tt3532216</imdb>
                <title>American Made</title>
                <year>2017</year>
        </meta>
        <link>
                <sublink>search</sublink>
                <sublink>searchsd</sublink>
        </link>
        <animated_thumbnail></animated_thumbnail>
        <thumbnail>https://image.tmdb.org/t/p/original/apgVqw0iOTniVh2O3cXfridDMOd.jpg</thumbnail>
        <animated_fanart></animated_fanart>
        <fanart>https://image.tmdb.org/t/p/original/qphzPbr42CaV6cayxOAsUbk8nLV.jpg</fanart>
</item>

<item>
        <title>The Foreigner (2017)</title>
        <meta>
                <content>movie</content>
                <imdb>tt1615160</imdb>
                <title>The Foreigner</title>
                <year>2017</year>
        </meta>
        <link>
                <sublink>search</sublink>
                <sublink>searchsd</sublink>
        </link>
        <animated_thumbnail></animated_thumbnail>
        <thumbnail>https://image.tmdb.org/t/p/original/rwM4hzrmc5HiWfQD9ls9DL4QgGl.jpg</thumbnail>
        <animated_fanart></animated_fanart>
        <fanart>https://image.tmdb.org/t/p/original/sDiGcjWhSu42dCw0jQmBInAkDZ9.jpg</fanart>
</item>

<item>
        <title>Three Billboards Outside Ebbing, Missouri (2017)</title>
        <meta>
                <content>movie</content>
                <imdb>tt5027774</imdb>
                <title>Three Billboards Outside Ebbing, Missouri</title>
                <year>2017</year>
        </meta>
        <link>
                <sublink>search</sublink>
                <sublink>searchsd</sublink>
        </link>
        <animated_thumbnail></animated_thumbnail>
        <thumbnail>https://image.tmdb.org/t/p/original/vgvw6w1CtcFkuXXn004S5wQsHRl.jpg</thumbnail>
        <animated_fanart></animated_fanart>
        <fanart>https://image.tmdb.org/t/p/original/huz4SOpcd2XjJiLVX6xmQZYiiDA.jpg</fanart>
</item>

<item>
        <title>Justice League (2017)</title>
        <meta>
                <content>movie</content>
                <imdb>tt0974015</imdb>
                <title>Justice League</title>
                <year>2017</year>
        </meta>
        <link>
                <sublink>search</sublink>
                <sublink>searchsd</sublink>
        </link>
        <animated_thumbnail></animated_thumbnail>
        <thumbnail>https://image.tmdb.org/t/p/w640/9rtrRGeRnL0JKtu9IMBWsmlmmZz.jpg</thumbnail>
        <animated_fanart></animated_fanart>
        <fanart>https://image.tmdb.org/t/p/original/pyxkLUfC5TG1pPoB4bwjCz8Z5iG.jpg</fanart>
</item>

<item>
        <title>Wonder Woman (2017)</title>
        <meta>
                <content>movie</content>
                <imdb>tt0451279</imdb>
                <title>Wonder Woman</title>
                <year>2017</year>
        </meta>
        <link>
                <sublink>search</sublink>
                <sublink>searchsd</sublink>
        </link>
        <animated_thumbnail></animated_thumbnail>
        <thumbnail>https://image.tmdb.org/t/p/original/imekS7f1OuHyUP2LAiTEM0zBzUz.jpg</thumbnail>
        <animated_fanart></animated_fanart>
        <fanart>https://image.tmdb.org/t/p/original/oM884oKelNJXILpnDevjHCAuLJq.jpg</fanart>
</item>

<item>
        <title>It (2017)</title>
        <meta>
                <content>movie</content>
                <imdb>tt1396484</imdb>
                <title>It</title>
                <year>2017</year>
        </meta>
        <link>
                <sublink>search</sublink>
                <sublink>searchsd</sublink>
        </link>
        <animated_thumbnail></animated_thumbnail>
        <thumbnail>https://image.tmdb.org/t/p/original/9E2y5Q7WlCVNEhP5GiVTjhEhx1o.jpg</thumbnail>
        <animated_fanart></animated_fanart>
        <fanart>https://image.tmdb.org/t/p/original/qVGpxnjrGlHaSTCqTQI6viBDSfp.jpg</fanart>
</item>

<item>
        <title>Thor: Ragnarok (2017)</title>
        <meta>
                <content>movie</content>
                <imdb>tt3501632</imdb>
                <title>Thor: Ragnarok</title>
                <year>2017</year>
        </meta>
        <link>
                <sublink>search</sublink>
                <sublink>searchsd</sublink>
        </link>
        <animated_thumbnail></animated_thumbnail>
        <thumbnail>https://image.tmdb.org/t/p/original/oSLd5GYGsiGgzDPKTwQh7wamO8t.jpg</thumbnail>
        <animated_fanart></animated_fanart>
        <fanart>https://image.tmdb.org/t/p/original/5wNUJs23rT5rTBacNyf5h83AynM.jpg</fanart>
</item>

<item>
        <title>Murder on the Orient Express (2017)</title>
        <meta>
                <content>movie</content>
                <imdb>tt3402236</imdb>
                <title>Murder on the Orient Express</title>
                <year>2017</year>
        </meta>
        <link>
                <sublink>search</sublink>
                <sublink>searchsd</sublink>
        </link>
        <animated_thumbnail></animated_thumbnail>
        <thumbnail>https://image.tmdb.org/t/p/original/iBlfxlw8qwtUS0R8YjIU7JtM6LM.jpg</thumbnail>
        <animated_fanart></animated_fanart>
        <fanart>https://image.tmdb.org/t/p/original/2J283YNxKhxAqHeVegUJ5mzLfGb.jpg</fanart>
</item>

<item>
        <title>Jigsaw (2017)</title>
        <meta>
                <content>movie</content>
                <imdb>tt3348730</imdb>
                <title>Jigsaw</title>
                <year>2017</year>
        </meta>
        <link>
                <sublink>search</sublink>
                <sublink>searchsd</sublink>
        </link>
        <animated_thumbnail></animated_thumbnail>
        <thumbnail>https://image.tmdb.org/t/p/original/zUbUtxiTdEgWnkXY945gtYYqBZ1.jpg</thumbnail>
        <animated_fanart></animated_fanart>
        <fanart>https://image.tmdb.org/t/p/original/25oR30jxA2TQkUhzmtBN4Ed0xxg.jpg</fanart>
</item>

<item>
        <title>Blade Runner 2049 (2017)</title>
        <meta>
                <content>movie</content>
                <imdb>tt1856101</imdb>
                <title>Blade Runner 2049</title>
                <year>2017</year>
        </meta>
        <link>
                <sublink>search</sublink>
                <sublink>searchsd</sublink>
        </link>
        <animated_thumbnail></animated_thumbnail>
        <thumbnail>https://image.tmdb.org/t/p/original/aMpyrCizvSdc0UIMblJ1srVgAEF.jpg</thumbnail>
        <animated_fanart></animated_fanart>
        <fanart>https://image.tmdb.org/t/p/original/m7ynwXIvSnhxQPR6pOICrC0L2sO.jpg</fanart>
</item>

<item>
        <title>A Bad Moms Christmas (2017)</title>
        <meta>
                <content>movie</content>
                <imdb>tt6359956</imdb>
                <title>A Bad Moms Christmas</title>
                <year>2017</year>
        </meta>
        <link>
                <sublink>search</sublink>
                <sublink>searchsd</sublink>
        </link>
        <animated_thumbnail></animated_thumbnail>
        <thumbnail>https://image.tmdb.org/t/p/original/gPNHolu7AGnrB7r5kvJRRTfwMFR.jpg</thumbnail>
        <animated_fanart></animated_fanart>
        <fanart>https://image.tmdb.org/t/p/original/xpbY5tIYPchAI1J5hHiMnUarRs5.jpg</fanart>
</item>

<item>
        <title>Coco (2017)</title>
        <meta>
                <content>movie</content>
                <imdb>tt2380307</imdb>
                <title>Coco</title>
                <year>2017</year>
        </meta>
        <link>
                <sublink>search</sublink>
                <sublink>searchsd</sublink>
        </link>
        <animated_thumbnail></animated_thumbnail>
        <thumbnail>https://image.tmdb.org/t/p/original/eKi8dIrr8voobbaGzDpe8w0PVbC.jpg</thumbnail>
        <animated_fanart></animated_fanart>
        <fanart>https://image.tmdb.org/t/p/original/gKZAQ3b9yApxFunUBlS5Mp74QG4.jpg</fanart>
</item>

<item>
        <title>Daddy's Home 2 (2017)</title>
        <meta>
                <content>movie</content>
                <imdb>tt5657846</imdb>
                <title>Daddy's Home 2</title>
                <year>2017</year>
        </meta>
        <link>
                <sublink>search</sublink>
                <sublink>searchsd</sublink>
        </link>
        <animated_thumbnail></animated_thumbnail>
        <thumbnail>https://image.tmdb.org/t/p/original/rF2IoKL0IFmumEXQFUuB8LajTYP.jpg</thumbnail>
        <animated_fanart></animated_fanart>
        <fanart>https://image.tmdb.org/t/p/original/jRi6AKMPLnMtsFtWY0FUXZOlnVb.jpg</fanart>
</item>

<item>
        <title>Valerian and the City of a Thousand Planets (2017)</title>
        <meta>
                <content>movie</content>
                <imdb>tt2239822</imdb>
                <title>Valerian and the City of a Thousand Planets</title>
                <year>2017</year>
        </meta>
        <link>
                <sublink>search</sublink>
                <sublink>searchsd</sublink>
        </link>
        <animated_thumbnail></animated_thumbnail>
        <thumbnail>https://image.tmdb.org/t/p/original/jfIpMh79fGRqYJ6PwZLCntzgxlF.jpg</thumbnail>
        <animated_fanart></animated_fanart>
        <fanart>https://image.tmdb.org/t/p/original/eOrSe2fOWeVOUjWhfwSmdk6V0Wm.jpg</fanart>
</item>

<item>
        <title>American Assassin (2017)</title>
        <meta>
                <content>movie</content>
                <imdb>tt1961175</imdb>
                <title>American Assassin</title>
                <year>2017</year>
        </meta>
        <link>
                <sublink>search</sublink>
                <sublink>searchsd</sublink>
        </link>
        <animated_thumbnail></animated_thumbnail>
        <thumbnail>https://image.tmdb.org/t/p/original/1UFz4TrbVdwBaJTz0rZn3PFI5kp.jpg</thumbnail>
        <animated_fanart></animated_fanart>
        <fanart>https://image.tmdb.org/t/p/original/9bowzDmB0XOnRfQ0EcezTFrncDP.jpg</fanart>
</item>

<item>
        <title>Wonder (2017)</title>
        <meta>
                <content>movie</content>
                <imdb>tt2543472</imdb>
                <title>Wonder</title>
                <year>2017</year>
        </meta>
        <link>
                <sublink>search</sublink>
                <sublink>searchsd</sublink>
        </link>
        <animated_thumbnail></animated_thumbnail>
        <thumbnail>https://image.tmdb.org/t/p/original/iWjUKwPJ91nFoltlZzr8s4Ij5da.jpg</thumbnail>
        <animated_fanart></animated_fanart>
        <fanart>https://image.tmdb.org/t/p/original/AczzhsH7SzFzM7qRctAZBNId3s.jpg</fanart>
</item>

<item>
        <title>Suburbicon (2017)</title>
        <meta>
                <content>movie</content>
                <imdb>tt0491175</imdb>
                <title>Suburbicon</title>
                <year>2017</year>
        </meta>
        <link>
                <sublink>search</sublink>
                <sublink>searchsd</sublink>
        </link>
        <animated_thumbnail></animated_thumbnail>
        <thumbnail>https://image.tmdb.org/t/p/original/a3IHgSwO5jWPLcGjKqbQ7pxVGkq.jpg</thumbnail>
        <animated_fanart></animated_fanart>
        <fanart>https://image.tmdb.org/t/p/original/zA5zlFVa76LdHmlFQrXaBW4XSvG.jpg</fanart>
</item>

<item>
        <title>The Killing of a Sacred Deer (2017)</title>
        <meta>
                <content>movie</content>
                <imdb>tt5715874</imdb>
                <title>The Killing of a Sacred Deer</title>
                <year>2017</year>
        </meta>
        <link>
                <sublink>search</sublink>
                <sublink>searchsd</sublink>
        </link>
        <animated_thumbnail></animated_thumbnail>
        <thumbnail>https://image.tmdb.org/t/p/original/e4DGlsc9g0h5AyoyvvAuIRnofN7.jpg</thumbnail>
        <animated_fanart></animated_fanart>
        <fanart>https://image.tmdb.org/t/p/original/854uDv6rzbwF82jOtFe931SMrRs.jpg</fanart>
</item>

<item>
        <title>Geostorm (2017)</title>
        <meta>
                <content>movie</content>
                <imdb>tt1981128</imdb>
                <title>Geostorm</title>
                <year>2017</year>
        </meta>
        <link>
                <sublink>search</sublink>
                <sublink>searchsd</sublink>
        </link>
        <animated_thumbnail></animated_thumbnail>
        <thumbnail>https://image.tmdb.org/t/p/original/nrsx0jEaBgXq4PWo7SooSnYJTv.jpg</thumbnail>
        <animated_fanart></animated_fanart>
        <fanart>https://image.tmdb.org/t/p/original/6jrMdMe4sMygTcJPpQTjKPmP4l0.jpg</fanart>
</item>

<item>
        <title>Logan Lucky (2017)</title>
        <meta>
                <content>movie</content>
                <imdb>tt5439796</imdb>
                <title>Logan Lucky</title>
                <year>2017</year>
        </meta>
        <link>
                <sublink>search</sublink>
                <sublink>searchsd</sublink>
        </link>
        <animated_thumbnail></animated_thumbnail>
        <thumbnail>https://image.tmdb.org/t/p/original/p1RDYsRvrm6v5gSKkVm0KOotUcE.jpg</thumbnail>
        <animated_fanart></animated_fanart>
        <fanart>https://image.tmdb.org/t/p/original/eszmHIWJHAKdnJcE3KcvVzOb6Jd.jpg</fanart>
</item>

<item>
        <title>Spider-Man: Homecoming (2017)</title>
        <meta>
                <content>movie</content>
                <imdb>tt2250912</imdb>
                <title>Spider-Man: Homecoming</title>
                <year>2017</year>
        </meta>
        <link>
                <sublink>search</sublink>
                <sublink>searchsd</sublink>
        </link>
        <animated_thumbnail></animated_thumbnail>
        <thumbnail>https://image.tmdb.org/t/p/original/kY2c7wKgOfQjvbqe7yVzLTYkxJO.jpg</thumbnail>
        <animated_fanart></animated_fanart>
        <fanart>https://image.tmdb.org/t/p/original/tPpYGm2mVecue7Bk3gNVoSPA5qn.jpg</fanart>
</item>

<item>
        <title>Atomic Blonde (2017)</title>
        <meta>
                <content>movie</content>
                <imdb>tt2406566</imdb>
                <title>Atomic Blonde</title>
                <year>2017</year>
        </meta>
        <link>
                <sublink>search</sublink>
                <sublink>searchsd</sublink>
        </link>
        <animated_thumbnail></animated_thumbnail>
        <thumbnail>https://image.tmdb.org/t/p/original/kV9R5h0Yct1kR8Hf8sJ1nX0Vz4x.jpg</thumbnail>
        <animated_fanart></animated_fanart>
        <fanart>https://image.tmdb.org/t/p/original/lj3wkYkJGkfmDfXkKrVarSJpFD4.jpg</fanart>
</item>

<item>
        <title>Hostiles (2017)</title>
        <meta>
                <content>movie</content>
                <imdb>tt5478478</imdb>
                <title>Hostiles</title>
                <year>2017</year>
        </meta>
        <link>
                <sublink>search</sublink>
                <sublink>searchsd</sublink>
        </link>
        <animated_thumbnail></animated_thumbnail>
        <thumbnail>https://image.tmdb.org/t/p/original/sd2f8Wzvwnn1sw94bBEc4RPH06.jpg</thumbnail>
        <animated_fanart></animated_fanart>
        <fanart>https://image.tmdb.org/t/p/original/j4F5Bd1pT2KUNToejtXkxVgrBQ3.jpg</fanart>
</item>

<item>
        <title>Wind River (2017)</title>
        <meta>
                <content>movie</content>
                <imdb>tt5362988</imdb>
                <title>Wind River</title>
                <year>2017</year>
        </meta>
        <link>
                <sublink>search</sublink>
                <sublink>searchsd</sublink>
        </link>
        <animated_thumbnail></animated_thumbnail>
        <thumbnail>https://image.tmdb.org/t/p/original/pySivdR845Hom4u4T2WNkJxe6Ad.jpg</thumbnail>
        <animated_fanart></animated_fanart>
        <fanart>https://image.tmdb.org/t/p/original/zcbb4XArMpGSNUQUZTdemp2WOTs.jpg</fanart>
</item>

<item>
        <title>Lady Bird (2017)</title>
        <meta>
                <content>movie</content>
                <imdb>tt4925292</imdb>
                <title>Lady Bird</title>
                <year>2017</year>
        </meta>
        <link>
                <sublink>search</sublink>
                <sublink>searchsd</sublink>
        </link>
        <animated_thumbnail></animated_thumbnail>
        <thumbnail>https://image.tmdb.org/t/p/original/pVtoXPA2zqNTeaR8MOsrD1XvUXK.jpg</thumbnail>
        <animated_fanart></animated_fanart>
        <fanart>https://image.tmdb.org/t/p/original/2ByWxoMbfE3pxztCJn5qTJ5Ui2Y.jpg</fanart>
</item>

<item>
        <title>The Star (2017)</title>
        <meta>
                <content>movie</content>
                <imdb>tt4587656</imdb>
                <title>The Star</title>
                <year>2017</year>
        </meta>
        <link>
                <sublink>search</sublink>
                <sublink>searchsd</sublink>
        </link>
        <animated_thumbnail></animated_thumbnail>
        <thumbnail>https://image.tmdb.org/t/p/original/tEbDvivUfsCupngKIfMJJ725eAD.jpg</thumbnail>
        <animated_fanart></animated_fanart>
        <fanart>https://image.tmdb.org/t/p/original/iJ5dkwIHQnq8dfmwSLh7dpETNhi.jpg</fanart>
</item>

<item>
        <title>Home Again (2017)</title>
        <meta>
                <content>movie</content>
                <imdb>tt5719700</imdb>
                <title>Home Again</title>
                <year>2017</year>
        </meta>
        <link>
                <sublink>search</sublink>
                <sublink>searchsd</sublink>
        </link>
        <animated_thumbnail></animated_thumbnail>
        <thumbnail>https://image.tmdb.org/t/p/original/z5CtCxpblBke2G8c7CMkstedMgY.jpg</thumbnail>
        <animated_fanart></animated_fanart>
        <fanart>https://image.tmdb.org/t/p/original/96K1pWr33W2QSiguMbmWiEZ2Zfl.jpg</fanart>
</item>

<item>
        <title>Bombshell: The Hedy Lamarr Story (2017)</title>
        <meta>
                <content>movie</content>
                <imdb>tt6752848</imdb>
                <title>Bombshell: The Hedy Lamarr Story</title>
                <year>2017</year>
        </meta>
        <link>
                <sublink>search</sublink>
                <sublink>searchsd</sublink>
        </link>
        <animated_thumbnail></animated_thumbnail>
        <thumbnail>https://image.tmdb.org/t/p/original/7kZonXfPuXZzwZIu9f7YPQmFXWQ.jpg</thumbnail>
        <animated_fanart></animated_fanart>
        <fanart>https://image.tmdb.org/t/p/original/mAXf3qtPr862mc198J2oRWPPA13.jpg</fanart>
</item>
