
################################################################################
<poster>Tikkes</poster>
<cache>10800</poster>
<thumbnail></thumbnail>
<fanart></fanart>
################################################################################

<item>
    <title>Riverdale S01E01 - Chapter One: The River's Edge</title>
    <meta>
        <content>episode</content>
        <imdb>tt5420376</imdb>
        <tvdb>311954</tvdb>
        <tvshowtitle>Riverdale</tvshowtitle>
        <year>2017</year>
        <title>Chapter One: The River's Edge</title>
        <premiered>2017-01-26</premiered>
        <season>1</season>
        <episode>1</episode>
    </meta>
    <link>
        <sublink>search</sublink>
        <sublink>searchsd</sublink>
    </link>
    <animated_thumbnail></animated_thumbnail>
    <thumbnail></thumbnail>
    <animated_fanart></animated_fanart>
    <fanart></fanart>
</item>
<item>
    <title>Riverdale S01E02 - Chapter Two: A Touch of Evil</title>
    <meta>
        <content>episode</content>
        <imdb>tt5420376</imdb>
        <tvdb>311954</tvdb>
        <tvshowtitle>Riverdale</tvshowtitle>
        <year>2017</year>
        <title>Chapter Two: A Touch of Evil</title>
        <premiered>2017-02-02</premiered>
        <season>1</season>
        <episode>2</episode>
    </meta>
    <link>
        <sublink>search</sublink>
        <sublink>searchsd</sublink>
    </link>
    <animated_thumbnail></animated_thumbnail>
    <thumbnail></thumbnail>
    <animated_fanart></animated_fanart>
    <fanart></fanart>
</item>
<item>
    <title>Riverdale S01E03 - Chapter Three: Body Double</title>
    <meta>
        <content>episode</content>
        <imdb>tt5420376</imdb>
        <tvdb>311954</tvdb>
        <tvshowtitle>Riverdale</tvshowtitle>
        <year>2017</year>
        <title>Chapter Three: Body Double</title>
        <premiered>2017-02-09</premiered>
        <season>1</season>
        <episode>3</episode>
    </meta>
    <link>
        <sublink>search</sublink>
        <sublink>searchsd</sublink>
    </link>
    <animated_thumbnail></animated_thumbnail>
    <thumbnail></thumbnail>
    <animated_fanart></animated_fanart>
    <fanart></fanart>
</item>
<item>
    <title>Riverdale S01E04 - Chapter Four: The Last Picture Show</title>
    <meta>
        <content>episode</content>
        <imdb>tt5420376</imdb>
        <tvdb>311954</tvdb>
        <tvshowtitle>Riverdale</tvshowtitle>
        <year>2017</year>
        <title>Chapter Four: The Last Picture Show</title>
        <premiered>2017-02-16</premiered>
        <season>1</season>
        <episode>4</episode>
    </meta>
    <link>
        <sublink>search</sublink>
        <sublink>searchsd</sublink>
    </link>
    <animated_thumbnail></animated_thumbnail>
    <thumbnail></thumbnail>
    <animated_fanart></animated_fanart>
    <fanart></fanart>
</item>
<item>
    <title>Riverdale S01E05 - Chapter Five: Heart of Darkness</title>
    <meta>
        <content>episode</content>
        <imdb>tt5420376</imdb>
        <tvdb>311954</tvdb>
        <tvshowtitle>Riverdale</tvshowtitle>
        <year>2017</year>
        <title>Chapter Five: Heart of Darkness</title>
        <premiered>2017-02-23</premiered>
        <season>1</season>
        <episode>5</episode>
    </meta>
    <link>
        <sublink>search</sublink>
        <sublink>searchsd</sublink>
    </link>
    <animated_thumbnail></animated_thumbnail>
    <thumbnail></thumbnail>
    <animated_fanart></animated_fanart>
    <fanart></fanart>
</item>
<item>
    <title>Riverdale S01E06 - Chapter Six: Faster, Pussycats! Kill! Kill!</title>
    <meta>
        <content>episode</content>
        <imdb>tt5420376</imdb>
        <tvdb>311954</tvdb>
        <tvshowtitle>Riverdale</tvshowtitle>
        <year>2017</year>
        <title>Chapter Six: Faster, Pussycats! Kill! Kill!</title>
        <premiered>2017-03-02</premiered>
        <season>1</season>
        <episode>6</episode>
    </meta>
    <link>
        <sublink>search</sublink>
        <sublink>searchsd</sublink>
    </link>
    <animated_thumbnail></animated_thumbnail>
    <thumbnail></thumbnail>
    <animated_fanart></animated_fanart>
    <fanart></fanart>
</item>
<item>
    <title>Riverdale S01E07 - Chapter Seven: In a Lonely Place</title>
    <meta>
        <content>episode</content>
        <imdb>tt5420376</imdb>
        <tvdb>311954</tvdb>
        <tvshowtitle>Riverdale</tvshowtitle>
        <year>2017</year>
        <title>Chapter Seven: In a Lonely Place</title>
        <premiered>2017-03-09</premiered>
        <season>1</season>
        <episode>7</episode>
    </meta>
    <link>
        <sublink>search</sublink>
        <sublink>searchsd</sublink>
    </link>
    <animated_thumbnail></animated_thumbnail>
    <thumbnail></thumbnail>
    <animated_fanart></animated_fanart>
    <fanart></fanart>
</item>
<item>
    <title>Riverdale S01E08 - Chapter Eight: The Outsiders</title>
    <meta>
        <content>episode</content>
        <imdb>tt5420376</imdb>
        <tvdb>311954</tvdb>
        <tvshowtitle>Riverdale</tvshowtitle>
        <year>2017</year>
        <title>Chapter Eight: The Outsiders</title>
        <premiered>2017-03-30</premiered>
        <season>1</season>
        <episode>8</episode>
    </meta>
    <link>
        <sublink>search</sublink>
        <sublink>searchsd</sublink>
    </link>
    <animated_thumbnail></animated_thumbnail>
    <thumbnail></thumbnail>
    <animated_fanart></animated_fanart>
    <fanart></fanart>
</item>
<item>
    <title>Riverdale S01E09 - Chapter Nine: La Grande Illusion</title>
    <meta>
        <content>episode</content>
        <imdb>tt5420376</imdb>
        <tvdb>311954</tvdb>
        <tvshowtitle>Riverdale</tvshowtitle>
        <year>2017</year>
        <title>Chapter Nine: La Grande Illusion</title>
        <premiered>2017-04-06</premiered>
        <season>1</season>
        <episode>9</episode>
    </meta>
    <link>
        <sublink>search</sublink>
        <sublink>searchsd</sublink>
    </link>
    <animated_thumbnail></animated_thumbnail>
    <thumbnail></thumbnail>
    <animated_fanart></animated_fanart>
    <fanart></fanart>
</item>
<item>
    <title>Riverdale S01E10 - Chapter Ten: The Lost Weekend</title>
    <meta>
        <content>episode</content>
        <imdb>tt5420376</imdb>
        <tvdb>311954</tvdb>
        <tvshowtitle>Riverdale</tvshowtitle>
        <year>2017</year>
        <title>Chapter Ten: The Lost Weekend</title>
        <premiered>2017-04-13</premiered>
        <season>1</season>
        <episode>10</episode>
    </meta>
    <link>
        <sublink>search</sublink>
        <sublink>searchsd</sublink>
    </link>
    <animated_thumbnail></animated_thumbnail>
    <thumbnail></thumbnail>
    <animated_fanart></animated_fanart>
    <fanart></fanart>
</item>
<item>
    <title>Riverdale S01E11 - Chapter Eleven: To Riverdale and Back Again</title>
    <meta>
        <content>episode</content>
        <imdb>tt5420376</imdb>
        <tvdb>311954</tvdb>
        <tvshowtitle>Riverdale</tvshowtitle>
        <year>2017</year>
        <title>Chapter Eleven: To Riverdale and Back Again</title>
        <premiered>2017-04-27</premiered>
        <season>1</season>
        <episode>11</episode>
    </meta>
    <link>
        <sublink>search</sublink>
        <sublink>searchsd</sublink>
    </link>
    <animated_thumbnail></animated_thumbnail>
    <thumbnail></thumbnail>
    <animated_fanart></animated_fanart>
    <fanart></fanart>
</item>
<item>
    <title>Riverdale S01E12 - Chapter Twelve: Anatomy of a Murder</title>
    <meta>
        <content>episode</content>
        <imdb>tt5420376</imdb>
        <tvdb>311954</tvdb>
        <tvshowtitle>Riverdale</tvshowtitle>
        <year>2017</year>
        <title>Chapter Twelve: Anatomy of a Murder</title>
        <premiered>2017-05-04</premiered>
        <season>1</season>
        <episode>12</episode>
    </meta>
    <link>
        <sublink>search</sublink>
        <sublink>searchsd</sublink>
    </link>
    <animated_thumbnail></animated_thumbnail>
    <thumbnail></thumbnail>
    <animated_fanart></animated_fanart>
    <fanart></fanart>
</item>
<item>
    <title>Riverdale S01E13 - Chapter Thirteen: The Sweet Hereafter</title>
    <meta>
        <content>episode</content>
        <imdb>tt5420376</imdb>
        <tvdb>311954</tvdb>
        <tvshowtitle>Riverdale</tvshowtitle>
        <year>2017</year>
        <title>Chapter Thirteen: The Sweet Hereafter</title>
        <premiered>2017-05-11</premiered>
        <season>1</season>
        <episode>13</episode>
    </meta>
    <link>
        <sublink>search</sublink>
        <sublink>searchsd</sublink>
    </link>
    <animated_thumbnail></animated_thumbnail>
    <thumbnail></thumbnail>
    <animated_fanart></animated_fanart>
    <fanart></fanart>
</item>