
################################################################################
<poster>Tikkes</poster>
<cache>10800</poster>
<thumbnail></thumbnail>
<fanart></fanart>
################################################################################

<item>
    <title>RocketJump: The Show S00E01 - Short: The Good, The Fast and The Furious</title>
    <meta>
        <content>episode</content>
        <imdb>tt5122514</imdb>
        <tvdb>302734</tvdb>
        <tvshowtitle>RocketJump: The Show</tvshowtitle>
        <year>2015</year>
        <title>Short: The Good, The Fast and The Furious</title>
        <premiered>2015-12-02</premiered>
        <season>0</season>
        <episode>1</episode>
    </meta>
    <link>
        <sublink>search</sublink>
        <sublink>searchsd</sublink>
    </link>
    <animated_thumbnail></animated_thumbnail>
    <thumbnail></thumbnail>
    <animated_fanart></animated_fanart>
    <fanart></fanart>
</item>
<item>
    <title>RocketJump: The Show S00E02 - Short: Fan Friction</title>
    <meta>
        <content>episode</content>
        <imdb>tt5122514</imdb>
        <tvdb>302734</tvdb>
        <tvshowtitle>RocketJump: The Show</tvshowtitle>
        <year>2015</year>
        <title>Short: Fan Friction</title>
        <premiered>2015-12-02</premiered>
        <season>0</season>
        <episode>2</episode>
    </meta>
    <link>
        <sublink>search</sublink>
        <sublink>searchsd</sublink>
    </link>
    <animated_thumbnail></animated_thumbnail>
    <thumbnail></thumbnail>
    <animated_fanart></animated_fanart>
    <fanart></fanart>
</item>
<item>
    <title>RocketJump: The Show S00E03 - Short: Truck Flipper v Bus Puncher</title>
    <meta>
        <content>episode</content>
        <imdb>tt5122514</imdb>
        <tvdb>302734</tvdb>
        <tvshowtitle>RocketJump: The Show</tvshowtitle>
        <year>2015</year>
        <title>Short: Truck Flipper v Bus Puncher</title>
        <premiered>2015-12-09</premiered>
        <season>0</season>
        <episode>3</episode>
    </meta>
    <link>
        <sublink>search</sublink>
        <sublink>searchsd</sublink>
    </link>
    <animated_thumbnail></animated_thumbnail>
    <thumbnail></thumbnail>
    <animated_fanart></animated_fanart>
    <fanart></fanart>
</item>
<item>
    <title>RocketJump: The Show S00E04 - Short: Freddie's Vlog</title>
    <meta>
        <content>episode</content>
        <imdb>tt5122514</imdb>
        <tvdb>302734</tvdb>
        <tvshowtitle>RocketJump: The Show</tvshowtitle>
        <year>2015</year>
        <title>Short: Freddie's Vlog</title>
        <premiered>2015-12-16</premiered>
        <season>0</season>
        <episode>4</episode>
    </meta>
    <link>
        <sublink>search</sublink>
        <sublink>searchsd</sublink>
    </link>
    <animated_thumbnail></animated_thumbnail>
    <thumbnail></thumbnail>
    <animated_fanart></animated_fanart>
    <fanart></fanart>
</item>
<item>
    <title>RocketJump: The Show S00E05 - Short: Walk and Talk</title>
    <meta>
        <content>episode</content>
        <imdb>tt5122514</imdb>
        <tvdb>302734</tvdb>
        <tvshowtitle>RocketJump: The Show</tvshowtitle>
        <year>2015</year>
        <title>Short: Walk and Talk</title>
        <premiered>2015-12-23</premiered>
        <season>0</season>
        <episode>5</episode>
    </meta>
    <link>
        <sublink>search</sublink>
        <sublink>searchsd</sublink>
    </link>
    <animated_thumbnail></animated_thumbnail>
    <thumbnail></thumbnail>
    <animated_fanart></animated_fanart>
    <fanart></fanart>
</item>
<item>
    <title>RocketJump: The Show S00E06 - Short: Jess' Big Date</title>
    <meta>
        <content>episode</content>
        <imdb>tt5122514</imdb>
        <tvdb>302734</tvdb>
        <tvshowtitle>RocketJump: The Show</tvshowtitle>
        <year>2015</year>
        <title>Short: Jess' Big Date</title>
        <premiered>2015-12-30</premiered>
        <season>0</season>
        <episode>6</episode>
    </meta>
    <link>
        <sublink>search</sublink>
        <sublink>searchsd</sublink>
    </link>
    <animated_thumbnail></animated_thumbnail>
    <thumbnail></thumbnail>
    <animated_fanart></animated_fanart>
    <fanart></fanart>
</item>
<item>
    <title>RocketJump: The Show S00E07 - Short: Keep off the Grass</title>
    <meta>
        <content>episode</content>
        <imdb>tt5122514</imdb>
        <tvdb>302734</tvdb>
        <tvshowtitle>RocketJump: The Show</tvshowtitle>
        <year>2016</year>
        <title>Short: Keep off the Grass</title>
        <premiered>2016-01-05</premiered>
        <season>0</season>
        <episode>7</episode>
    </meta>
    <link>
        <sublink>search</sublink>
        <sublink>searchsd</sublink>
    </link>
    <animated_thumbnail></animated_thumbnail>
    <thumbnail></thumbnail>
    <animated_fanart></animated_fanart>
    <fanart></fanart>
</item>
<item>
    <title>RocketJump: The Show S00E08 - Short: Tip Jar</title>
    <meta>
        <content>episode</content>
        <imdb>tt5122514</imdb>
        <tvdb>302734</tvdb>
        <tvshowtitle>RocketJump: The Show</tvshowtitle>
        <year>2016</year>
        <title>Short: Tip Jar</title>
        <premiered>2016-01-12</premiered>
        <season>0</season>
        <episode>8</episode>
    </meta>
    <link>
        <sublink>search</sublink>
        <sublink>searchsd</sublink>
    </link>
    <animated_thumbnail></animated_thumbnail>
    <thumbnail></thumbnail>
    <animated_fanart></animated_fanart>
    <fanart></fanart>
</item>